zillow_scraper/__init__.py
zillow_scraper/scraper.py
zillow_scraper-0.1.1.dist-info/METADATA
zillow_scraper-0.1.1.dist-info/WHEEL
zillow_scraper-0.1.1.dist-info/top_level.txt
zillow_scraper-0.1.1.dist-info/RECORD
