Metadata-Version: 2.1
Name: zillow-scraper
Version: 0.1.1
Summary: A web scraper for Zillow real estate listings.
Home-page: https://github.com/Adeyemi0/zillow_scraper
Author: Adeyemi
Author-email: xmine4346@gmail.com
License: UNKNOWN
Platform: UNKNOWN
Classifier: Programming Language :: Python :: 3
Classifier: License :: OSI Approved :: MIT License
Classifier: Operating System :: OS Independent
Requires-Python: >=3.6
Requires-Dist: requests
Requires-Dist: beautifulsoup4
Requires-Dist: pandas
Requires-Dist: fake-useragent
Requires-Dist: streamlit
